hangman_jg/__init__.py
hangman_jg/hangman_main.py
hangman_jg/tempCodeRunnerFile.py
hangman_jg-0.4.dist-info/METADATA
hangman_jg-0.4.dist-info/WHEEL
hangman_jg-0.4.dist-info/top_level.txt
hangman_jg-0.4.dist-info/RECORD
